__init__.py
settings_loader/__init__.py
settings_loader/core.py
settingsloadertypesafe-0.2.4.dist-info/licenses/LICENSE
settingsloadertypesafe-0.2.4.dist-info/METADATA
settingsloadertypesafe-0.2.4.dist-info/WHEEL
settingsloadertypesafe-0.2.4.dist-info/top_level.txt
settingsloadertypesafe-0.2.4.dist-info/RECORD
