Metadata-Version: 2.4
Name: SettingsLoaderTypeSafe
Version: 0.2.4
Summary: Type safe settings loader for python - support for env, args, secrets and app setttings
Author: aqzi
License: MIT License
Project-URL: Homepage, https://github.com/aqzi/SettingsLoader
Project-URL: Repository, https://github.com/aqzi/SettingsLoader
Requires-Python: >=3.8
License-File: LICENSE
Requires-Dist: pydantic
Requires-Dist: python-dotenv
Requires-Dist: pyyaml
Dynamic: license-file
